ml_loggers/__init__.py
ml_loggers/config.py
ml_loggers/console_logger.py
ml_loggers/file_logger.py
ml_loggers/logger.py
ml_loggers/multi_logger.py
ml_loggers/wandb_logger.py
ml_loggers-1.1.0.dist-info/METADATA
ml_loggers-1.1.0.dist-info/WHEEL
ml_loggers-1.1.0.dist-info/licenses/LICENSE
ml_loggers-1.1.0.dist-info/RECORD
