Metadata-Version: 2.1
Name: ml_loggers
Version: 1.1.0
Summary: A collection of loggers for machine learning experiments.
Project-URL: Homepage, https://github.com/serhez/ml-loggers
Project-URL: Issues, https://github.com/serhez/ml-loggers/issues
Author-email: Sergio Hernandez Gutierrez <contact.sergiohernandez@gmail.com>
License-File: LICENSE
Classifier: License :: OSI Approved :: MIT License
Classifier: Operating System :: OS Independent
Classifier: Programming Language :: Python :: 3
Requires-Python: >=3.10
Requires-Dist: hydra-core
Requires-Dist: numpy
Requires-Dist: termcolor
Requires-Dist: wandb
